Metadata-Version: 2.1
Name: trujillo-azure-package
Version: 0.1.0
Summary: Paquete que tiene como proposito el brindar clases de permitan utilizar servicios de Microsoft Azure
Home-page: UNKNOWN
Author: Fernando Colque
Author-email: fernando.colque@terranovatrading.com.pe
License: MIT
Platform: UNKNOWN
